{
  "advancements": [
    {
      "conditions": [
        {
          "config": "terraincognita:ginkgo",
          "type": "cuneiform:config"
        }
      ],
      "advancement": {
        "parent": "minecraft:recipes/root",
        "rewards": {
          "recipes": [
            "terraincognita:crafting/ginkgo_planks"
          ]
        },
        "criteria": {
          "has_any_ginkgo_logs": {
            "trigger": "minecraft:inventory_changed",
            "conditions": {
              "items": [
                {
                  "tag": "terraincognita:ginkgo_logs"
                }
              ]
            }
          },
          "has_the_recipe": {
            "trigger": "minecraft:recipe_unlocked",
            "conditions": {
              "recipe": "terraincognita:crafting/ginkgo_planks"
            }
          }
        },
        "requirements": [
          [
            "has_any_ginkgo_logs",
            "has_the_recipe"
          ]
        ]
      }
    }
  ]
}